autogitsync/__init__.py
autogitsync-0.5.0.dist-info/WHEEL
autogitsync-0.5.0.dist-info/entry_points.txt
autogitsync-0.5.0.dist-info/METADATA
autogitsync-0.5.0.dist-info/RECORD
