Metadata-Version: 2.4
Name: autogitsync
Version: 0.5.0
Summary: Automatically sync outgoing local changes with a remote repository.
Author: Rodrigo Girão Serrão
Author-email: Rodrigo Girão Serrão <5621605+rodrigogiraoserrao@users.noreply.github.com>
License-Expression: MIT
Classifier: Development Status :: 4 - Beta
Classifier: Environment :: Console
Classifier: Intended Audience :: Developers
Classifier: Intended Audience :: Education
Classifier: Intended Audience :: End Users/Desktop
Classifier: License :: OSI Approved :: MIT License
Classifier: Topic :: Education
Classifier: Typing :: Typed
Requires-Dist: click>=8.2.1
Requires-Dist: gitpython>=3.1.45
Requires-Dist: rich>=14.1.0
Requires-Python: >=3.12
Project-URL: Documentation, https://github.com/rodrigogiraoserrao/autogitsync/blob/main/README.md
Project-URL: Issues, https://github.com/rodrigogiraoserrao/autogitsync/issues
Project-URL: Repository, https://github.com/rodrigogiraoserrao/autogitsync
